Workbook

Sheet Test User Data
A2: Test Data / User Accounts
A3: Test Data | B3: Description | C3: User ID
A4: V1 | B4: Anonymous visitor (not signed in) | C4: NA
A5: B1 | B5: Signed-in buyer, not enrolled in any course (default buyer; QA100 allowed) | C5: shivamnamdev.edu@gmail.com
A6: B2 | B6: Signed-in buyer enrolled in Course A only (restricted-coupon 'wrong user'; mobile buyer) | C6: mavish.ps8@gmail.com
A7: S1 | B7: Enrolled student: Course B (closed cohort) and, when a test grants it, the open fixture course | C7: financetrail.bazar@gmail.com
A8: A1 | B8: Admin user (checks activity log / enrolment list) | C8: shivamnamdev.corp@gmail.com
A9: C1 | B9: Open paid course: QA fixture 'QA Checkout Sandbox' (qa-checkout-sandbox), INR 10 / USD 1, NEXT_PUBLIC_QA_FIXTURES=1 | C9: /courses/qa-checkout-sandbox
A10: C2 | B10: Closed cohort: any real course, e.g. Git Beginner Live Session (git-beginner-batch-1) | C10: /courses/git-beginner-batch-1
A11: K1 | B11: Percentage coupon, public: BIRTHDAY20 (20% off) | C11: BIRTHDAY20
A12: K2 | B12: Fixed coupon, public, larger than the QA price: EXISTINGSTUDENT_BATCH03 (INR 1999 / USD 50 off): makes C1 free | C12: EXISTINGSTUDENT_BATCH03
A13: K3 | B13: Restricted coupon for other accounts only: SHIVAMSPECIAL | C13: SHIVAMSPECIAL
A14: K4 | B14: QA-only 100% coupon for B1 and B2: QA100 (exists only with the QA flag and user list) | C14: QA100
A16: Notes | B16: Course A = python-beginners-batch-2 (closed), Course B = git-beginner-batch-1 (closed). Gateway: mocked Razorpay stub unless a case says 'real test-mode'. Never use live keys.

Sheet Buy Now Entry and CTA States
A1: TC ID | B1: Scenario | C1: Preconditions | D1: Steps | E1: Expected Result | F1: Priority | G1: Result | H1: PRD Scenario | I1: Automated
A2: CHK-ENTRY-001 | B2: Buy Now (INR) shown on an open cohort | C2: B1 signed in; C1 open; not enrolled | D2: 1. Open /courses/qa-checkout-sandbox | E2: Buy Now (INR) is visible and enabled; no Enrollment Closed panel | F2: P0 | H2: CK-01 | I2: CDP-CTA-001 (pricing-currency-coupon.spec.ts)
A3: CHK-ENTRY-002 | B3: Currency toggle changes the button label | C3: B1 on C1 | D3: 1. Click International | E3: Button label becomes Buy Now (USD); price shows $1 | F3: P0 | H3: CK-02 | I3: CDP-CUR-002/005 (pricing-currency-coupon.spec.ts)
A4: CHK-ENTRY-003 | B4: Switching back restores the INR label | C4: ENTRY-002 done | D4: 1. Click India | E4: Button label returns to Buy Now (INR); price shows INR 10 | F4: P1 | H4: CK-02 | I4: CDP-CUR-009
A5: CHK-ENTRY-004 | B5: Closed cohort shows Enrollment Closed and no Buy Now | C5: Any user; C2 closed | D5: 1. Open /courses/git-beginner-batch-1 | E5: Enrollment Closed heading and View Open Cohorts are shown; no Buy Now, no coupon box | F5: P0 | H5: CK-03 | I5: tests/ui/sales-funnel.spec.ts (@smoke)
A6: CHK-ENTRY-005 | B6: View Open Cohorts leads to the catalog | C6: C2 closed | D6: 1. Click View Open Cohorts | E6: User lands on /courses | F6: P1 | H6: CK-03 | I6: No
A7: CHK-ENTRY-006 | B7: Visitor click on Buy Now asks to sign in | C7: V1 on C1 | D7: 1. Click Buy Now (INR) | E7: Alert 'Please log in or create an account first to secure your spot!' appears and the Clerk sign-in opens | F7: P0 | H7: CK-04 | I7: No
A8: CHK-ENTRY-007 | B8: Visitor click sends no order request | C8: V1 on C1; network log open | D8: 1. Click Buy Now (INR) 2. Accept the alert | E8: No request to /api/create-order is made; no Razorpay script is loaded | F8: P0 | H8: CK-04 | I8: No
A9: CHK-ENTRY-008 | B9: After sign-in the buyer returns to the same course page | C9: ENTRY-006 done | D9: 1. Sign in as B1 in the Clerk window | E9: Buyer is back on /courses/qa-checkout-sandbox with Buy Now available | F9: P1 | H9: CK-04 | I9: No
A10: CHK-ENTRY-009 | B10: Visitor coupon Apply also asks to sign in | C10: V1 on C1 | D10: 1. Type a code 2. Click Apply | E10: Alert 'Please log in first to apply a coupon!' and Clerk sign-in; no coupon is applied | F10: P1 | H10: CK-04 | I10: No
A11: CHK-ENTRY-010 | B11: Enrolled student on an open cohort sees Go to Dashboard | C11: S1 granted C1 for the test | D11: 1. Open C1 | E11: 'You are Enrolled! Go to Dashboard' is shown; no Buy Now; no coupon box | F11: P0 | H11: CK-05 | I11: tests/ui/discovery/checkout-real-db.spec.ts (CDP-ENR-001)
A12: CHK-ENTRY-011 | B12: Enrolled student on a closed cohort sees Go to Dashboard | C12: S1 enrolled in Course B | D12: 1. Open C2 | E12: 'You are Enrolled! Go to Dashboard' is shown instead of View Open Cohorts | F12: P0 | H12: CK-05 | I12: tests/ui/auth (state S2)
A13: CHK-ENTRY-012 | B13: Go to Dashboard from the sales page opens the dashboard | C13: ENTRY-010 state | D13: 1. Click Go to Dashboard | E13: User lands on /learning | F13: P1 | H13: CK-05 | I13: CDP-ENR-003
... A16: CHK-ENTRY-015 | B16: Buy Now is keyboard operable | C16: B1 on C1 | D16: 1. Tab to Buy Now 2. Press Enter | E16: Order request is sent exactly once | F16: P1 | H16: CK-01 | I16: CDP-CTA-012
F17: Coverage | G17: =IF(COUNTA(A2:A16)=0,0,(COUNTIF(G2:G16,"Passed")+COUNTIF(G2:G16,"Failed")+COUNTIF(G2:G16,"NA"))/COUNTA(A2:A16))

Sheet Order Creation and Request
A1: TC ID | B1: Scenario | C1: Preconditions | D1: Steps | E1: Expected Result | F1: Priority | G1: Result | H1: PRD Scenario | I1: Automated
A2: CHK-ORDER-001 | B2: Processing state while the order is created | C2: B1 on C1; create-order slowed to 2 s | D2: 1. Click Buy Now (INR) | E2: Button shows Processing…, is disabled and shows a spinner | F2: P0 | H2: CK-06 | I2: CDP-CTA-007/008
A3: CHK-ORDER-002 | B3: Button recovers after the order response | C3: ORDER-001 | D3: 1. Wait for the response | E3: Processing state ends (button enabled again or overlay opens) | F3: P1 | H3: CK-06 | I3: tests/ui/discovery/checkout-flow.spec.ts
A4: CHK-ORDER-003 | B4: Order request carries only course, currency and coupon | C4: B1 on C1; network log | D4: 1. Click Buy Now (INR) with no coupon | E4: POST /api/create-order body is {courseId, currency:'INR'}; no price, user id or slug | F4: P0 | H4: CK-07 | I4: CDP-PAY-001 (checkout-flow.spec.ts)
A5: CHK-ORDER-004 | B5: Coupon code is sent when applied | C5: B1 on C1 | D5: 1. Apply K1 2. Click Buy Now | E5: Body also contains couponCode 'BIRTHDAY20' | F5: P0 | H5: CK-07 | I5: CDP-E2E-001
A6: CHK-ORDER-005 | B6: Currency is sent as USD after the toggle | C6: B1 on C1 | D6: 1. Click International 2. Click Buy Now (USD) | E6: Body has currency 'USD' | F6: P0 | H6: CK-07 | I6: CDP-PAY-003/005
A7: CHK-ORDER-006 | B7: Razorpay script is requested | C7: B1 on C1 | D7: 1. Click Buy Now | E7: checkout.razorpay.com/v1/checkout.js is requested before the order call | F7: P1 | H7: CK-08 | I7: No
A8: CHK-ORDER-007 | B8: create-order 401 shows the server message | C8: B1; response forced to 401 | D8: 1. Click Buy Now | E8: Alert shows the message (401 Unauthorized); button enabled; overlay not opened | F8: P0 | H8: CK-25 | I8: No
A9: CHK-ORDER-008 | B9: create-order 400 (closed cohort / unknown course) is surfaced | C9: Response forced to 400 | D9: 1. Click Buy Now | E9: Alert with the server error; button enabled; no overlay | F9: P0 | H9: CK-25 | I9: No
A10: CHK-ORDER-009 | B10: create-order 403 restricted coupon is surfaced | C10: B2 on C1 with K3 | D10: 1. Apply K3 (UI blocks) or force the request 2. Click Buy Now | E10: Server message 'This coupon is not valid for your account.' is shown; no overlay | F10: P0 | H10: CK-14 | I10: No
A11: CHK-ORDER-010 | B11: create-order 500 shows a recoverable error | C11: Response forced to 500 | D11: 1. Click Buy Now | E11: Alert with the error; Buy Now enabled again; no overlay; no success modal | F11: P0 | H11: CK-25 | I11: CDP-ERR-004 / CDP-PAY-010
A12: CHK-ORDER-011 | B12: Network drop while creating the order | C12: Request aborted | D12: 1. Click Buy Now | E12: Alert 'Something went wrong connecting to the payment gateway.' (or error); button recovers; retry works | F12: P0 | H12: CK-25 | I12: CDP-PAY-010 / CDP-ERR-009
A13: CHK-ORDER-012 | B13: Order timeout ends the loading state | C13: Request delayed beyond 30 s | D13: 1. Click Buy Now | E13: Loading state ends with a clear error or retry; page usable | F13: P1 | H13: CK-25 | I13: No
... A15: CHK-ORDER-014 | B15: Order is rejected for an unauthenticated API call | C15: No session | D15: 1. POST /api/create-order | E15: 401; no order | F15: P0 | H15: CK-25 | I15: tests/api/crm.spec.ts
F16: Coverage | G16: =IF(COUNTA(A2:A15)=0,0,(COUNTIF(G2:G15,"Passed")+COUNTIF(G2:G15,"Failed")+COUNTIF(G2:G15,"NA"))/COUNTA(A2:A15))

Sheet Razorpay Overlay and Amount Int
A1: TC ID | B1: Scenario | C1: Preconditions | D1: Steps | E1: Expected Result | F1: Priority | G1: Result | H1: PRD Scenario | I1: Automated
A2: CHK-AMT-001 | B2: Overlay opens after the order is created | C2: B1 on C1; gateway mocked | D2: 1. Click Buy Now (INR) | E2: Razorpay overlay opens exactly once | F2: P0 | H2: CK-08 | I2: CDP-PAY-002
A3: CHK-AMT-002 | B3: Overlay shows the order id, name and description | C3: AMT-001 | D3: 1. Inspect the options passed to Razorpay | E3: order_id is the created order; name 'Shivam Academy'; description 'Enrollment: QA Checkout Sandbox' | F3: P1 | H3: CK-08 | I3: CDP-PAY-002
A4: CHK-AMT-003 | B4: Overlay theme colour | C4: AMT-001 | D4: 1. Inspect options | E4: theme.color is #f59e0b | F4: P1 | H4: CK-08 | I4: No
A5: CHK-AMT-004 | B5: Overlay never exposes the secret key | C5: AMT-001 | D5: 1. Inspect options and page source | E5: Only the public key id appears; no key secret anywhere on the client | F5: P0 | H5: CK-08 | I5: No
A6: CHK-AMT-005 | B6: Overlay prefill uses the signed-in user | C6: B1 on C1 | D6: 1. Open the overlay | E6: prefill.name and prefill.email equal B1's name and email | F6: P1 | H6: CK-09 | I6: checkout-real-gateway.spec.ts (email shown in the real overlay)
A7: CHK-AMT-006 | B7: INR order amount in paise | C7: B1 on C1 | D7: 1. Click Buy Now (INR) | E7: Order amount 1000 paise (INR 10 x 100), currency INR | F7: P0 | H7: CK-10 | I7: CDP-PAY-001/004; real order: CDP-PAY-003 (checkout-real-db.spec.ts)
A8: CHK-AMT-007 | B8: USD order amount in cents | C8: B1 on C1 | D8: 1. Click International 2. Click Buy Now (USD) | E8: Order amount 100 cents ($1 x 100), currency USD | F8: P0 | H8: CK-11 | I8: CDP-PAY-005
A9: CHK-AMT-008 | B9: Percentage coupon: INR amount | C9: B1 on C1 with K1 applied | D9: 1. Click Buy Now | E9: Displayed INR 8; order amount 800 paise | F9: P0 | H9: CK-12 | I9: CDP-PAY-003 (real order API)
A10: CHK-AMT-009 | B10: Percentage coupon: USD amount | C10: B1 on C1 with K1, USD | D10: 1. Click Buy Now (USD) | E10: Displayed $0.80; order amount 80 cents | F10: P0 | H10: CK-12 | I10: No
A11: CHK-AMT-010 | B11: Fixed coupon larger than the price | C11: B1 on C1 with K2 | D11: 1. Check the button | E11: Price floors at INR 0 / $0 and the CTA is Enroll for Free (no paid order; see PRD 05). Note: C1 is too cheap to show a non-zero fixed discount | F11: P0 | H11: CK-13 | I11: CDP-PRICE-010
A12: CHK-AMT-011 | B12: Restricted coupon for another user is refused | C12: B2 on C1 | D12: 1. Apply K3 | E12: Message 'This coupon is restricted to specific accounts.'; price unchanged; Buy Now unchanged | F12: P0 | H12: CK-14 | I12: CDP-COUP-006
A13: CHK-AMT-012 | B13: Restricted coupon forced to the server | C13: B2; call create-order with K3 | D13: 1. POST /api/create-order {couponCode:'SHIVAMSPECIAL'} | E13: 403 'This coupon is not valid for your account.'; no order | F13: P0 | H13: CK-14 | I13: No
... A19: CHK-AMT-018 | B19: Amounts never go below one currency unit on a paid order | C19: K2 forced to the order API | D19: 1. POST create-order with K2 on C1 | E19: Server creates a paid order of at least 1 unit or refuses; never 0 or negative | F19: P1 | H19: CK-13 | I19: No
F20: Coverage | G20: =IF(COUNTA(A2:A19)=0,0,(COUNTIF(G2:G19,"Passed")+COUNTIF(G2:G19,"Failed")+COUNTIF(G2:G19,"NA"))/COUNTA(A2:A19))

Sheet Payment Success and Verificatio
A1: TC ID | B1: Scenario | C1: Preconditions | D1: Steps | E1: Expected Result | F1: Priority | G1: Result | H1: PRD Scenario | I1: Automated
A2: CHK-PAY-001 | B2: Paid happy path, INR | C2: B1 on C1; gateway mocked | D2: 1. Click Buy Now (INR) 2. Trigger payment success | E2: Welcome Aboard! modal appears after verify-payment returns success | F2: P0 | H2: CK-15 | I2: CDP-PAY-006 / CDP-E2E-001
A3: CHK-PAY-002 | B3: Paid happy path, USD | C3: B1 on C1, USD | D3: 1. Click Buy Now (USD) 2. Trigger success | E3: Same as PAY-001; receipt shows $ | F3: P0 | H3: CK-16 | I3: No
A4: CHK-PAY-003 | B4: Paid happy path with a coupon | C4: B1 on C1 with K1 | D4: 1. Buy Now 2. Success | E4: Order and receipt use the discounted amount (INR 8) | F4: P0 | H4: CK-12/15 | I4: CDP-E2E-001
A5: CHK-PAY-004 | B5: Verification request carries only the three Razorpay fields | C5: PAY-001; network log | D5: 1. Inspect POST /api/verify-payment | E5: Body has razorpay_order_id, razorpay_payment_id, razorpay_signature only: no slug, user id or price | F5: P0 | H5: CK-17 | I5: CDP-PAY-006
A6: CHK-PAY-005 | B6: Success modal only after the server confirms | C6: Verify delayed 2 s | D6: 1. Trigger success 2. Look before the response | E6: No modal until verify-payment returns success: true | F6: P0 | H6: CK-15 | I6: No
A7: CHK-PAY-006 | B7: One enrollment row is created | C7: PAY-001; QA database | D7: 1. Read user_enrollments for B1 and C1 | E7: Exactly one row with the right course slug | F7: P0 | H7: CK-15 | I7: No
A8: CHK-PAY-007 | B8: Admin activity log entry | C8: PAY-001; A1 | D8: 1. Open the admin activity log | E8: An enrollment entry for B1 and C1 exists | F8: P1 | H8: CK-27 | I8: No
A9: CHK-PAY-008 | B9: Verification 400 (invalid signature) is surfaced | C9: Verify forced to 400 | D9: 1. Trigger success | E9: Alert shows the message ('Invalid payment signature'); no modal; no enrollment | F9: P0 | H9: CK-22 | I9: CDP-PAY-011 / CDP-ERR-006
A10: CHK-PAY-009 | B10: Verification 500 is surfaced | C10: Verify forced to 500 | D10: 1. Trigger success | E10: Alert 'Error verifying enrollment.' (or server text); no modal | F10: P0 | H10: CK-22 | I10: No
A11: CHK-PAY-010 | B11: Verification network failure | C11: Verify aborted | D11: 1. Trigger success | E11: Alert 'Error verifying enrollment.'; no modal; page usable | F11: P0 | H11: CK-22 | I11: No
A12: CHK-PAY-011 | B12: Order of another account is refused | C12: Order created by B1, verified as B2 | D12: 1. Verify B1's order while signed in as B2 | E12: 403 'This order belongs to a different account.'; no enrollment | F12: P0 | H12: CK-23 | I12: No
A13: CHK-PAY-012 | B13: Tampered signature grants nothing | C13: B1; real verify API | D13: 1. POST verify-payment with a wrong signature | E13: 400; no row in user_enrollments | F13: P0 | H13: CK-23 | I13: CDP-ERR-006 (checkout-real-db.spec.ts)
... A15: CHK-PAY-014 | B15: Unauthenticated verify call | C15: No session | D15: 1. POST /api/verify-payment | E15: 401 | F15: P0 | H15: CK-23 | I15: No
F16: Coverage | G16: =IF(COUNTA(A2:A15)=0,0,(COUNTIF(G2:G15,"Passed")+COUNTIF(G2:G15,"Failed")+COUNTIF(G2:G15,"NA"))/COUNTA(A2:A15))

Sheet Payment Failure and Recovery
A1: TC ID | B1: Scenario | C1: Preconditions | D1: Steps | E1: Expected Result | F1: Priority | G1: Result | H1: PRD Scenario | I1: Automated
A2: CHK-FAIL-001 | B2: Payment failed message | C2: B1 on C1; overlay open | D2: 1. Trigger payment.failed | E2: Alert 'Payment failed or was cancelled. Please try again.'; no success modal | F2: P0 | H2: CK-20 | I2: CDP-PAY-008 / CDP-ERR-005
A3: CHK-FAIL-002 | B3: Nothing is granted after a failure | C3: FAIL-001 | D3: 1. Check the enrolment and the page | E3: No row in user_enrollments; CTA is still Buy Now | F3: P0 | H3: CK-20 | I3: No
A4: CHK-FAIL-003 | B4: Retry after a failure creates a new order | C4: FAIL-001 | D4: 1. Click Buy Now again | E4: A second order is created and the overlay opens again without a reload | F4: P0 | H4: CK-20 | I4: CDP-E2E-008
A5: CHK-FAIL-004 | B5: Overlay dismissed without paying | C5: Overlay open | D5: 1. Close the overlay | E5: Page stays usable; Buy Now is usable; no modal | F5: P1 | H5: CK-21 | I5: CDP-PAY-009
A6: CHK-FAIL-005 | B6: Buy Now while the overlay is still open | C6: Overlay open | D6: 1. Click Buy Now behind the overlay | E6: Observe: known gap R-CK-5 (button is enabled and a second order can be created) | F6: P1 | H6: CK-21 | I6: No
A7: CHK-FAIL-006 | B7: Razorpay script blocked | C7: B1 on C1; request to checkout.js blocked | D7: 1. Click Buy Now | E7: Alert 'Razorpay SDK failed to load. Are you online?'; button enabled; no order created | F7: P0 | H7: CK-24 | I7: No
A8: CHK-FAIL-007 | B8: Script recovers after going online | C8: FAIL-006 | D8: 1. Unblock 2. Click Buy Now | E8: Order is created and the overlay opens | F8: P1 | H8: CK-24 | I8: No
A9: CHK-FAIL-008 | B9: Refresh while Processing… | C9: Order slowed | D9: 1. Click Buy Now 2. Refresh the page | E9: Page loads normally; no stuck state; no enrollment | F9: P1 | H9: CK-25 | I9: No
A10: CHK-FAIL-009 | B10: Back navigation while the modal is open | C10: Success modal visible | D10: 1. Press Back | E10: Page leaves cleanly; the enrollment stays; no duplicate on return | F10: P1 | H10: CK-27 | I10: No
A11: CHK-FAIL-010 | B11: Paid at the gateway but verification never arrives | C11: Network drops after payment | D11: 1. Pay 2. Cut the network before verify | E11: Buyer sees an error; known gap R-CK-3 (no webhook fallback): enrolment missing; report as accepted risk | F11: P0 | H11: CK-22 | I11: No
A12: CHK-FAIL-011 | B12: Failure does not break coupon and currency state | C12: FAIL-001 | D12: 1. Check price, coupon and currency | E12: Previously chosen currency and coupon are unchanged | F12: P1 | H12: CK-20 | I12: No
F13: Coverage | G13: =IF(COUNTA(A2:A12)=0,0,(COUNTIF(G2:G12,"Passed")+COUNTIF(G2:G12,"Failed")+COUNTIF(G2:G12,"NA"))/COUNTA(A2:A12))

Sheet Duplicates and Idempotency
A1: TC ID | B1: Scenario | C1: Preconditions | D1: Steps | E1: Expected Result | F1: Priority | G1: Result | H1: PRD Scenario | I1: Automated
A2: CHK-IDEM-001 | B2: Double-click creates one order | C2: B1 on C1; order slowed | D2: 1. Double-click Buy Now | E2: One create-order request; one overlay | F2: P0 | H2: CK-26 | I2: CDP-CTA-009 / CDP-RACE-001
A3: CHK-IDEM-002 | B3: Rapid repeated clicks | C3: Same | D3: 1. Click 4 times quickly | E3: Still one order | F3: P0 | H3: CK-26 | I3: CDP-RACE-001
A4: CHK-IDEM-003 | B4: Repeat verification creates one enrollment | C4: PAY-001 done | D4: 1. POST verify-payment again with the same ids | E4: Success answer; still one row for B1 and C1 | F4: P0 | H4: CK-27 | I4: No
A5: CHK-IDEM-004 | B5: Repeat verification sends one email | C5: IDEM-003 | D5: 1. Check the inbox (label [QA-AUTOMATION]) | E5: Exactly one welcome/receipt email | F5: P1 | H5: CK-27 | I5: No
A6: CHK-IDEM-005 | B6: Repeat verification adds no second activity log row | C6: IDEM-003 | D6: 1. Open the activity log | E6: One entry only | F6: P1 | H6: CK-27 | I6: No
A7: CHK-IDEM-006 | B7: Enrolled buyer cannot start another purchase | C7: S1 granted C1 | D7: 1. Open C1 | E7: No Buy Now; Go to Dashboard shown | F7: P0 | H7: CK-28 | I7: CDP-ENR-004
A8: CHK-IDEM-007 | B8: Two tabs, second purchase attempt | C8: B1 enrolled in tab 1; stale tab 2 shows Buy Now | D8: 1. Click Buy Now in tab 2 | E8: Server or UI handles it: no second enrollment row (report order created for an enrolled user as a finding) | F8: P1 | H8: CK-27 | I8: No
A9: CHK-IDEM-008 | B9: Concurrent verification of the same payment | C9: Two verify calls in parallel | D9: 1. Send both | E9: One enrollment row (known race R-FE-1 in PRD 05 applies) | F9: P0 | H9: CK-27 | I9: CDP-RACE-003 (free path)
F10: Coverage | G10: =IF(COUNTA(A2:A9)=0,0,(COUNTIF(G2:G9,"Passed")+COUNTIF(G2:G9,"Failed")+COUNTIF(G2:G9,"NA"))/COUNTA(A2:A9))

Sheet Post-Purchase State and Hand-of
A1: TC ID | B1: Scenario | C1: Preconditions | D1: Steps | E1: Expected Result | F1: Priority | G1: Result | H1: PRD Scenario | I1: Automated
A2: CHK-POST-001 | B2: Success modal content | C2: PAY-001 | D2: 1. Read the modal | E2: Heading Welcome Aboard!, text about the WhatsApp group, buttons Join WhatsApp Group and Go to Dashboard | F2: P0 | H2: CK-18 | I2: CDP-PAY-006
A3: CHK-POST-002 | B3: WhatsApp link attributes | C3: POST-001 | D3: 1. Inspect Join WhatsApp Group | E3: href is the course WhatsApp link; target _blank; rel noreferrer | F3: P1 | H3: CK-18 | I3: No
A4: CHK-POST-003 | B4: WhatsApp link opens in a new tab | C4: POST-001 | D4: 1. Click Join WhatsApp Group | E4: New tab opens; the original page remains on the modal | F4: P1 | H4: CK-18 | I4: No
A5: CHK-POST-004 | B5: Go to Dashboard routes into the learning area | C5: POST-001 | D5: 1. Click Go to Dashboard | E5: Lands on /learning (the dashboard); this is the intended destination (owner decision 2026-10-29) | F5: P0 | H5: CK-19 | I5: CDP-PAY-007 / CDP-RED-001
A6: CHK-POST-005 | B6: Dashboard lists the new course | C6: POST-004 | D6: 1. Look at My Enrolled Courses | E6: The purchased course is listed | F6: P0 | H6: CK-15 | I6: No
A7: CHK-POST-006 | B7: Course page after purchase shows enrolled | C7: POST-001 | D7: 1. Open /courses/qa-checkout-sandbox | E7: 'You are Enrolled! Go to Dashboard'; no Buy Now; no coupon box | F7: P0 | H7: CK-28 | I7: CDP-FREE-011 / CDP-CTA-004
A8: CHK-POST-007 | B8: State survives reload | C8: POST-006 | D8: 1. Reload | E8: Same enrolled state | F8: P1 | H8: CK-28 | I8: CDP-ENR-005
A9: CHK-POST-008 | B9: Course page opens for the buyer | C9: POST-004 | D9: 1. Open /learning/qa-checkout-sandbox | E9: Course content loads (no redirect away) | F9: P0 | H9: CK-28 | I9: tests/ui/auth/access-control.spec.ts
A10: CHK-POST-009 | B10: Modal copy says the payment is verified (paid) | C10: POST-001 | D10: 1. Read the text | E10: 'Your payment is verified…' is accurate for a paid purchase (inaccurate for free: PRD 05 R-FE-2) | F10: P1 | H10: CK-18 | I10: No
A11: CHK-POST-010 | B11: One receipt email with order id and amount | C11: PAY-001; inbox label | D11: 1. Open the email | E11: Subject has the QA prefix; shows order id, amount and PAID; sent once | F11: P1 | H11: CK-27 | I11: No
A12: CHK-POST-011 | B12: Modal buttons have discernible names | C12: POST-001 | D12: 1. Inspect the accessibility tree | E12: Both buttons expose readable names | F12: P1 | H12: CK-36 | I12: No
F13: Coverage | G13: =IF(COUNTA(A2:A12)=0,0,(COUNTIF(G2:G12,"Passed")+COUNTIF(G2:G12,"Failed")+COUNTIF(G2:G12,"NA"))/COUNTA(A2:A12))

Sheet Mobile, Browsers and Accessibil
A1: TC ID | B1: Scenario | C1: Preconditions | D1: Steps | E1: Expected Result | F1: Priority | G1: Result | H1: PRD Scenario | I1: Automated
A2: CHK-XB-001 | B2: Checkout panel on a 390 px phone | C2: B2 signed in; mobile viewport | D2: 1. Open C1 | E2: Currency toggle, coupon box and Buy Now fully visible; no horizontal scroll | F2: P1 | H2: CK-32 | I2: CDP-UX-004/005/006
A3: CHK-XB-002 | B3: Mobile paid journey | C3: B2 on a phone | D3: 1. Apply K1 2. Tap Buy Now 3. Succeed | E3: Overlay opens, success modal fits the screen, buttons are tappable | F3: P1 | H3: CK-32 | I3: CDP-E2E-010
A4: CHK-XB-003 | B4: Success modal on a phone | C4: XB-002 | D4: 1. Look at the modal | E4: No clipped text; both buttons reachable without scrolling | F4: P1 | H4: CK-32 | I4: No
A5: CHK-XB-004 | B5: Firefox: paid happy path | C5: Firefox project | D5: 1. Run PAY-001 | E5: Same result as Chromium | F5: P1 | H5: CK-33 | I5: No
A6: CHK-XB-005 | B6: WebKit (Safari engine): paid happy path | C6: WebKit project | D6: 1. Run PAY-001 | E6: Same result as Chromium | F6: P1 | H6: CK-33 | I6: No
A7: CHK-XB-006 | B7: Keyboard: reach and use Buy Now | C7: B1 on C1 | D7: 1. Tab through the page 2. Enter on Buy Now | E7: Visible focus; order created | F7: P1 | H7: CK-36 | I7: CDP-CTA-012
A8: CHK-XB-007 | B8: Keyboard: success modal | C8: Modal visible | D8: 1. Tab between the two buttons 2. Enter | E8: Both work; focus stays inside the modal (note if it escapes) | F8: P1 | H8: CK-36 | I8: No
A9: CHK-XB-008 | B9: Blocking alert() dialogs | C9: Any error path | D9: 1. Trigger an error | E9: Message is readable; page resumes after OK (known limitation R-CK-6) | F9: P1 | H9: CK-36 | I9: No
F10: Coverage | G10: =IF(COUNTA(A2:A9)=0,0,(COUNTIF(G2:G9,"Passed")+COUNTIF(G2:G9,"Failed")+COUNTIF(G2:G9,"NA"))/COUNTA(A2:A9))

Sheet Real Gateway Sandbox (Test Mode
A1: TC ID | B1: Scenario | C1: Preconditions | D1: Steps | E1: Expected Result | F1: Priority | G1: Result | H1: PRD Scenario | I1: Automated
A2: CHK-REAL-001 | B2: Real test-mode overlay opens | C2: rzp_test_ keys only; B1 on C1 | D2: 1. Click Buy Now | E2: The real Razorpay overlay opens with INR 10 and the right prefill | F2: P1 | H2: CK-34 | I2: tests/ui/discovery/checkout-real-gateway.spec.ts (opt-in E2E_REAL_GATEWAY=1)
A3: CHK-REAL-002 | B3: Successful test card | C3: REAL-001 | D3: 1. Pay with the Razorpay test card | E3: Success handler runs; verify-payment succeeds; Welcome Aboard! modal; enrolment created | F3: P1 | H3: CK-34 | I3: tests/ui/discovery/checkout-real-gateway.spec.ts (opt-in E2E_REAL_GATEWAY=1)
A4: CHK-REAL-003 | B4: Failure test card | C4: REAL-001 | D4: 1. Pay with the failure test card | E4: 'Payment failed or was cancelled…' alert; nothing granted; retry possible | F4: P1 | H4: CK-35 | I4: tests/ui/discovery/checkout-real-gateway.spec.ts (opt-in E2E_REAL_GATEWAY=1)
A5: CHK-REAL-004 | B5: Live key guard | C5: Environment | D5: 1. Check RAZORPAY_KEY_ID and NEXT_PUBLIC_RAZORPAY_KEY_ID | E5: Both start with rzp_test_; a live key makes the suite fail before any test runs | F5: P0 | H5: CK-34 | I5: tests/ui/discovery/checkout-real-gateway.spec.ts (opt-in E2E_REAL_GATEWAY=1)
A6: CHK-REAL-005 | B6: Stub still matches the real overlay | C6: REAL-001/002 | D6: 1. Compare options and handler arguments with the mocked stub | E6: Same fields and shapes; update the stub if they differ | F6: P1 | H6: CK-34 | I6: Partly: the real test proves the same flow (checkout-real-gateway.spec.ts); the shape comparison is manual
F7: Coverage | G7: =IF(COUNTA(A2:A6)=0,0,(COUNTIF(G2:G6,"Passed")+COUNTIF(G2:G6,"Failed")+COUNTIF(G2:G6,"NA"))/COUNTA(A2:A6))

Sheet End-to-End Business-Critical
A1: TC ID | B1: Scenario | C1: Preconditions | D1: Steps | E1: Expected Result | F1: Priority | G1: Result | H1: PRD Scenario | I1: Automated
A2: CHK-E2E-001 | B2: Visitor to enrolled learner (INR) | C2: V1 starts on / | D2: 1. Open Courses 2. Open C1 3. Click Buy Now 4. Sign in as B1 5. Pay 6. Go to Dashboard | E2: Course is listed under My Enrolled Courses; one row; one email | F2: P0 | H2: CK-15 | I2: No
A3: CHK-E2E-002 | B3: Buyer with a percentage coupon | C3: B1 signed in | D3: 1. Apply K1 2. Buy Now 3. Pay | E3: Charged INR 8; enrolment row has the coupon; receipt amount INR 8 | F3: P0 | H3: CK-12/15 | I3: CDP-E2E-001
A4: CHK-E2E-003 | B4: International buyer (USD) | C4: B1 | D4: 1. Switch to International 2. Buy Now (USD) 3. Pay | E4: Charged $1; modal; enrolled | F4: P0 | H4: CK-16 | I4: No
A5: CHK-E2E-004 | B5: Failed payment then successful retry | C5: B1 | D5: 1. Buy Now 2. Fail 3. Buy Now 4. Pay | E5: One enrolment; two orders at the gateway; one success email | F5: P0 | H5: CK-20 | I5: CDP-E2E-008
A6: CHK-E2E-005 | B6: Restricted coupon, wrong user | C6: B2 | D6: 1. Apply K3 2. Try Buy Now | E6: Coupon refused; the buyer can still pay the full price | F6: P0 | H6: CK-14 | I6: CDP-E2E-005
A7: CHK-E2E-006 | B7: Enrolled student tries to buy again | C7: S1 enrolled in C1 | D7: 1. Open C1 | E7: Cannot start a purchase; Go to Dashboard | F7: P0 | H7: CK-28 | I7: CDP-E2E-004
A8: CHK-E2E-007 | B8: Closed cohort cannot be bought | C8: Any user | D8: 1. Open C2 2. Try the API directly | E8: UI has no Buy Now; API returns 400 | F8: P0 | H8: CK-03 | I8: tests/ui/sales-funnel.spec.ts
A9: CHK-E2E-008 | B9: Free-coupon journey hand-off | C9: B1 | D9: 1. Apply QA100 2. Enroll for Free | E9: No Razorpay; enrolled (full flow in PRD 05) | F9: P0 | H9: CK-31 | I9: CDP-E2E-003
A10: CHK-E2E-009 | B10: Mobile buyer | C10: B2 on a phone | D10: 1. Full paid flow | E10: All steps usable; enrolled | F10: P1 | H10: CK-32 | I10: CDP-E2E-010
A11: CHK-E2E-010 | B11: Admin sees the purchase | C11: A1 after E2E-001 | D11: 1. Open /admin | E11: The new enrolment and the activity entry are visible | F11: P1 | H11: CK-27 | I11: No
F12: Coverage | G12: =IF(COUNTA(A2:A11)=0,0,(COUNTIF(G2:G11,"Passed")+COUNTIF(G2:G11,"Failed")+COUNTIF(G2:G11,"NA"))/COUNTA(A2:A11))

Sheet Traceability to Functional Requ
A1: Requirement | B1: Coverage Rate
A2: FR1, FR2, FR12, FR13, FR14 (entry) — Buy Now Entry & CTA States | B2: ='Buy Now Entry and CTA States'!G17 | D2: Status | E2: Count
A3: FR3, FR4, FR20 — Order Creation & Request | B3: ='Order Creation and Request'!G16 | D3: Passed | E3: =COUNTIF('Buy Now Entry and CTA States'!G2:G16, "Passed") + COUNTIF('Order Creation and Request'!G2:G15, "Passed") + COUNTIF('Razorpay Overlay and Amount Int'!G2:G19, "Passed") + COUNTIF('Payment Success and Verificatio'!G2:G15, "Passed") + COUNTIF('Payment Failure and Recovery'!G2:G12, "Passed") + COUNTIF('Duplicates and Idempotency'!G2:G9, "Passed") + COUNTIF('Post-Purchase State and Hand-of'!G2:G12, "Passed") + COUNTIF('Mobile, Browsers and Accessibil'!G2:G9, "Passed") + COUNTIF('Real Gateway Sandbox (Test Mode'!G2:G6, "Passed") + COUNTIF('End-to-End Business-Critical'!G2:G11, "Passed")
A4: FR5, FR6, FR17, FR18 — Razorpay Overlay & Amount Integrity | B4: ='Razorpay Overlay and Amount Int'!G20 | D4: Failed | E4: =COUNTIF('Buy Now Entry and CTA States'!G2:G16, "Failed") + COUNTIF('Order Creation and Request'!G2:G15, "Failed") + COUNTIF('Razorpay Overlay and Amount Int'!G2:G19, "Failed") + COUNTIF('Payment Success and Verificatio'!G2:G15, "Failed") + COUNTIF('Payment Failure and Recovery'!G2:G12, "Failed") + COUNTIF('Duplicates and Idempotency'!G2:G9, "Failed") + COUNTIF('Post-Purchase State and Hand-of'!G2:G12, "Failed") + COUNTIF('Mobile, Browsers and Accessibil'!G2:G9, "Failed") + COUNTIF('Real Gateway Sandbox (Test Mode'!G2:G6, "Failed") + COUNTIF('End-to-End Business-Critical'!G2:G11, "Failed")
A5: FR7, FR8, FR16 (verification) — Payment Success & Verification | B5: ='Payment Success and Verificatio'!G16 | D5: Not Applicable | E5: =COUNTIF('Buy Now Entry and CTA States'!G2:G16, "NA") + COUNTIF('Order Creation and Request'!G2:G15, "NA") + COUNTIF('Razorpay Overlay and Amount Int'!G2:G19, "NA") + COUNTIF('Payment Success and Verificatio'!G2:G15, "NA") + COUNTIF('Payment Failure and Recovery'!G2:G12, "NA") + COUNTIF('Duplicates and Idempotency'!G2:G9, "NA") + COUNTIF('Post-Purchase State and Hand-of'!G2:G12, "NA") + COUNTIF('Mobile, Browsers and Accessibil'!G2:G9, "NA") + COUNTIF('Real Gateway Sandbox (Test Mode'!G2:G6, "NA") + COUNTIF('End-to-End Business-Critical'!G2:G11, "NA")
A6: FR9, FR10, FR11, FR20 — Payment Failure & Recovery | B6: ='Payment Failure and Recovery'!G13 | D6: Not Tested Yet | E6: =E7-E3-E4-E5
A7: FR14, FR15, FR21 — Duplicates & Idempotency | B7: ='Duplicates and Idempotency'!G10 | D7: Total Test Cases | E7: =COUNTA('Buy Now Entry and CTA States'!A2:A16) + COUNTA('Order Creation and Request'!A2:A15) + COUNTA('Razorpay Overlay and Amount Int'!A2:A19) + COUNTA('Payment Success and Verificatio'!A2:A15) + COUNTA('Payment Failure and Recovery'!A2:A12) + COUNTA('Duplicates and Idempotency'!A2:A9) + COUNTA('Post-Purchase State and Hand-of'!A2:A12) + COUNTA('Mobile, Browsers and Accessibil'!A2:A9) + COUNTA('Real Gateway Sandbox (Test Mode'!A2:A6) + COUNTA('End-to-End Business-Critical'!A2:A11)
A8: FR16, FR19, FR21 — Post-Purchase State & Hand-off | B8: ='Post-Purchase State and Hand-of'!G13
A9: FR22 — Mobile, Browsers & Accessibility | B9: ='Mobile, Browsers and Accessibil'!G10
A10: FR5, FR7, FR9 (real overlay) — Real Gateway Sandbox (Test Mode) | B10: ='Real Gateway Sandbox (Test Mode'!G7
A11: FR1 to FR19 (journeys) — End-to-End Business-Critical | B11: ='End-to-End Business-Critical'!G12
